{
    "name": "axe_back",
    "texture": {
        "path": "miapi:models/item/tool/head/axe_back/[material.texture].json",
        "transform": {
            "rotation": {
                "x": 0.0,
                "y": 0.0,
                "z": 0.0
            },
            "translation": {
                "x": 6.0,
                "y": 1.0,
                "z": 0.0
            },
            "scale": {
                "x": 1,
                "y": 1,
                "z": 1
            }
        }
    },
    "priority": 2,
    "repairPriority": 1,
    "materialProperty": [
        "default",
        "handheld",
        "tool",
        "head"
    ],
    "allowedInSlots": [
        "tool_head_back"
    ],
    "enchantments": {
        "allowed": [
            "miapi:tool"
        ]
    },
    "allowedMaterial": {
        "allowedMaterials": [
            "wood",
            "metal",
            "flint",
            "bone",
            "stone",
            "rod",
            "crystal"
        ],
        "cost": 2
    },
    "better_combat_config": {
        "parent": "bettercombat:double_axe"
    },
    "mining_level": {
        "axe": "[material.mining_level]-1"
    },
    "guiOffset": {
        "x": -1
    },
    "attributes": [
        {
            "attribute": "miapi:generic.mining_speed.axe",
            "value": "[material.mining_speed]* 0.5",
            "operation": "+",
            "slot": "mainhand"
        },
        {
            "attribute": "generic.attack_damage",
            "value": "floor((([material.hardness]-3.4)*2.3)^(1/3))+7 - floor([material.density]/4)*2 - 1",
            "operation": "+",
            "slot": "mainhand",
            "uuid": "CB3F55D3-645C-4F38-A497-9C13A33DB5CF"
        },
        {
            "attribute": "generic.attack_speed",
            "value": "+0.5",
            "operation": "+",
            "slot": "mainhand",
            "uuid": "FA233E1C-4180-4865-B01B-BCCE9785ACA3"
        }
    ],
    "durability": "[material.durability]* 0.5"
}