{
    "name": "tool_back",
    "texture": {
        "path": "miapi:models/item/tool/head/tool_back/[material.texture].json",
        "transform": {
            "rotation": {
                "x": 0.0,
                "y": 0.0,
                "z": 0.0
            },
            "translation": {
                "x": 0.0,
                "y": 0.0,
                "z": 0.0
            },
            "scale": {
                "x": 1,
                "y": 1,
                "z": 1
            }
        }
    },
    "priority": 0,
    "repairPriority": 1,
    "materialProperty": [
        "default",
        "handheld",
        "tool",
        "head"
    ],
    "allowedInSlots": [
        "tool_head_back"
    ],
    "enchantments": {
        "allowed": [
            "miapi:tool"
        ]
    },
    "attributes": [
        {
            "attribute": "miapi:generic.mining_speed.shovel",
            "value": "0.1",
            "operation": "*",
            "slot": "mainhand"
        },
        {
            "attribute": "miapi:generic.mining_speed.hoe",
            "value": "1 / 0.75 -1",
            "operation": "*",
            "slot": "mainhand"
        },
        {
            "attribute": "miapi:generic.mining_speed.pickaxe",
            "value": "0.1",
            "operation": "*",
            "slot": "mainhand"
        },
        {
            "attribute": "miapi:generic.mining_speed.axe",
            "value": "1 / 0.75 -1",
            "operation": "*",
            "slot": "mainhand"
        }
    ],
    "durability": "[material.durability]* 0.5",
    "allowedMaterial": {
        "allowedMaterials": [
            "wood",
            "metal",
            "flint",
            "bone",
            "stone",
            "rod",
            "crystal"
        ],
        "cost": 1
    }
}